[{"id": 5179, "gempId": "207_18", "side": "Light", "rarity": "U", "set": "207", "printings": [{"set": "207"}], "front": {"title": "\u2022Profundity", "imageUrl": "https://res.starwarsccg.org/cards/Virtual7-Light/large/profundity.gif", "type": "Starship", "subType": "Capital: Mon Calamari Star Cruiser", "uniqueness": "*", "destiny": "1", "power": "6", "armor": "7", "hyperspeed": "3", "deploy": "6", "forfeit": "8", "icons": ["Pilot", "Nav Computer", "Scomp Link"], "characteristics": ["Rebel (starship)", "ship-docking capability"], "gametext": "Deploys -2 to a system opponent occupies (-4 if opponent's system). May add 6 pilots, 8 passengers, 3 starfighters, 3 vehicles, and 1 corvette. Permanent pilot provides ability of 2.", "lore": "Blank."}, "pulledBy": ["Rebellions Are Built On Hope"], "legacy": false}]