[{"id": 1839, "gempId": "13_35", "side": "Light", "rarity": "PM", "set": "13", "printings": [{"set": "13"}], "front": {"title": "\u2022Only Jedi Carry That Weapon", "imageUrl": "https://res.starwarsccg.org/cards/ReflectionsIII-Light/large/onlyjedicarrythatweapon.gif", "type": "Defensive Shield", "uniqueness": "*", "destiny": "0", "icons": ["Defensive Shield", "Episode I"], "gametext": "Plays on table. For opponent to steal a weapon from target character using a non-[Episode I] card, must first draw destiny. If destiny +1 > target's ability, weapon stolen. Otherwise, attempt fails and stealing card is placed out of play.", "lore": "An elegant weapon for a more civilized age."}, "counterpart": "Weapon Of A Sith - Defensive Shield", "legacy": false}]