[{"id": 6834, "gempId": "213_46", "side": "Light", "rarity": "R2", "set": "213", "printings": [{"set": "213"}], "front": {"title": "\u2022Kessel Run (V)", "imageUrl": "https://res.starwarsccg.org/cards/Virtual13-Light/large/kesselrun.gif", "type": "Effect", "uniqueness": "*", "destiny": "5", "gametext": "Deploy on Kessel; draw 'coaxium' destinies, stacking face up here until total > 12 (cannot deploy otherwise). During each move phase, if your smuggler here, move a 'coaxium' card from here to Used Pile. If no 'coaxium' cards here, retrieve 4 Force; place Effect out of play.", "lore": "Planet Kessel has infamous glitterstim spice mines attracting smugglers and pirates. A 'Kessel run' is a long, dangerous hyper-route they must travel quickly."}, "pulledBy": ["The Signal", "We Wish To Board At Once"], "canceledBy": ["Oo-ta Goo-ta", "Solo?"], "legacy": false}]