[{"id": 5231, "gempId": "208_20", "side": "Light", "rarity": "U", "set": "208", "printings": [{"set": "208"}], "front": {"title": "\u2022Mandalorian Mishap (V)", "imageUrl": "https://res.starwarsccg.org/cards/Virtual8-Light/large/mandalorianmishap.gif", "type": "Interrupt", "subType": "Used", "uniqueness": "*", "destiny": "5", "icons": ["Jabba's Palace"], "gametext": "Cancel the game text of Jodo or any Fett for remainder of turn. OR Take Sabine, Under Attack, or a blaster into hand from Reserve Deck; reshuffle. OR During a battle, if opponent just drew more than two battle destiny, cancel one of those destiny draws (your choice).", "lore": "Most space-faring adventurers meet their fate with a calm, quiet dignity."}, "pulls": ["Sabine Wren", "Under Attack", "Amidala's Blaster", "BlasTech E-11B Blaster Rifle", "Blaster", "Blaster Rifle", "Blaster Rifle (V)", "Cloud City Blaster", "Echo Base Trooper Rifle", "Han's Heavy Blaster Pistol", "Han's Heavy Blaster Pistol (V)", "Lando's Blaster Rifle", "Leia's Blaster Rifle", "Leia's Sporting Blaster", "Luke's Blaster Pistol", "Luke's Blaster Pistol (V)", "Mos Eisley Blaster", "Naboo Blaster Rifle", "Naboo Security Office Blaster", "Panaka's Blaster", "Stun Blaster"], "legacy": false}]