[{"id": 5009, "gempId": "202_14", "side": "Dark", "rarity": "C2", "set": "202", "printings": [{"set": "202"}], "front": {"title": "\u2022Black 6", "imageUrl": "https://res.starwarsccg.org/cards/Virtual2-Dark/large/black6.gif", "type": "Starship", "subType": "Starfighter: TIE/LN", "uniqueness": "*", "destiny": "6", "power": "1", "maneuver": "4", "deploy": "1", "forfeit": "3", "characteristics": ["Imperial (starship)"], "gametext": "May add 1 pilot. While Tanbris piloting, power +1. Once per game, may retrieve bottom card of Lost Pile. Your total battle destiny here is +X, where X = this TIE's power - 5.", "lore": "Blank.", "extraText": ["No Hyperdrive"]}, "conceptBy": "(Original concept by Jan Westergard)", "matching": ["Lieutenant Tanbris"], "legacy": false}]