[{"id": 5714, "gempId": "14_19", "side": "Light", "rarity": "R", "set": "14", "printings": [{"set": "14"}], "front": {"title": "\u2022Mace Windu, Jedi Master (AI)", "imageUrl": "https://res.starwarsccg.org/cards/TheedPalace-Light/large/macewindujedimasterai.gif", "type": "Character", "subType": "Jedi Master", "destiny": "1", "power": "6", "ability": "7", "deploy": "8", "forfeit": "8", "icons": ["Warrior", "Episode I"], "gametext": "Deploys -2 on Naboo. While on Naboo, once during your control phase may use 1 Force to cancel Maul's immunity to attrition for remainder of turn. Immune to attrition < 3 (< 5 while on Naboo).", "lore": "Jedi Council member who is known to be one of the strongest members of the Council. Has come to Naboo to investigate the death of the mysterious 'dark warrior.'", "extraText": ["Jedi Master"]}, "legacy": false}]