[{"id": 6050, "gempId": "209_14", "side": "Light", "rarity": "R", "set": "209", "printings": [{"set": "209"}], "front": {"title": "\u2022Yoxgit (V)", "imageUrl": "https://res.starwarsccg.org/cards/Virtual9-Light/large/yoxgit.gif", "type": "Character", "subType": "Alien", "destiny": "3", "power": "1", "ability": "2", "deploy": "2", "forfeit": "3", "icons": ["Jabba's Palace"], "gametext": "Deploys free to (and power +2 at) a Cloud City, Jabba's Palace, or Maz's Castle location. Once per turn, if you just drew an alien (or [Independent] starship) for destiny, may take that card into hand to cancel and redraw that destiny.", "lore": "Male Ugnaught. Left Cloud City after the Empire took control. Works for Hermi Odle, helping to supply him with various weaponry. Hopes to someday return to Cloud City."}, "legacy": false}]