[{"id": 791, "gempId": "1_174", "side": "Dark", "rarity": "R1", "set": "1", "printings": [{"set": "1"}], "front": {"title": "\u2022DS-61-3", "imageUrl": "https://res.starwarsccg.org/cards/Premiere-Dark/large/ds613.gif", "type": "Character", "subType": "Imperial", "uniqueness": "*", "destiny": "2", "power": "3", "ability": "2", "deploy": "2", "forfeit": "3", "icons": ["Pilot", "Warrior"], "characteristics": ["Corellian"], "gametext": "Adds 3 to power of anything he pilots. When piloting Black 3, also adds 1 to maneuver and may draw one battle destiny if not able to otherwise.", "lore": "Vader's right wingman. Flies Black 3. Reputation for ferocity in combat. Corellian pilot with excellent skills. Nicknamed 'Backstabber.'"}, "pulledBy": ["Blizzard 4"], "matching": ["Black 3"], "legacy": false}]