[{"id": 1617, "gempId": "1_224", "side": "Dark", "rarity": "C2", "set": "1", "printings": [{"set": "1"}], "front": {"title": "Macroscan", "imageUrl": "https://res.starwarsccg.org/cards/Premiere-Dark/large/macroscan.gif", "type": "Effect", "destiny": "3", "gametext": "Use 2 Force to deploy near opponent's Reserve Deck. At any time, you may use 1 Force to peek at the top card of that deck. If 'nighttime conditions' exist anywhere on table, you may peek at the top three cards.", "lore": "Electrobinocular view. Readouts list object's true and relative azimuth, elevation and range. Built-in night vision."}, "pulledBy": ["Twi'lek Advisor", "We Must Accelerate Our Plans"], "legacy": false}]