[{"id": 2100, "gempId": "1_38", "side": "Light", "rarity": "C2", "set": "1", "printings": [{"set": "1"}], "front": {"title": "Restraining Bolt", "imageUrl": "https://res.starwarsccg.org/cards/Premiere-Light/large/restrainingbolt.gif", "type": "Device", "destiny": "6", "gametext": "Deploy on any droid at any site. Droid cannot move and cannot utilize its 'game text.' During your deploy phase, Restraining Bolt may be transferred (for free) to another droid at same site.", "lore": "Fits in a special socket on a droid's body. When installed, restricts actions of droids, forcing them to follow orders. Can be operated remotely by a 'caller.'"}, "pulledBy": ["Corporal Beezer", "Hero Of A Thousand Devices", "Portable Scanner"], "counterpart": "Restraining Bolt", "legacy": false}]