[{"id": 373, "gempId": "9_7", "side": "Light", "rarity": "U", "set": "9", "printings": [{"set": "9"}], "front": {"title": "\u2022Captain Verrack", "imageUrl": "https://res.starwarsccg.org/cards/DeathStarII-Light/large/captainverrack.gif", "type": "Character", "subType": "Rebel", "uniqueness": "*", "destiny": "3", "power": "2", "ability": "2", "deploy": "2", "forfeit": "4", "characteristics": ["gunner", "Mon Calamari"], "gametext": "Allows your starship weapons at same location to fire and deploy for 1 less Force. While aboard your capital starship, adds 1 to each of its weapon destiny draws (2 when targeting a capital starship).", "lore": "Mon Calamari computer technician. Expert in power systems. His skills are desperately needed by Rebel fleet. Gunner."}, "pulledBy": ["Admiral Ackbar"], "legacy": false}]