[{"id": 797, "gempId": "6_65", "side": "Light", "rarity": "U", "set": "6", "printings": [{"set": "6"}], "front": {"title": "\u2022Dune Sea Sabacc", "imageUrl": "https://res.starwarsccg.org/cards/JabbasPalace-Light/large/duneseasabacc.gif", "type": "Interrupt", "subType": "Used", "uniqueness": "*", "destiny": "5", "gametext": "Requirements: A Jawa at a Tatooine site. Wild cards (0-7): Sandcrawler sites, Magnetic Suction Tube, Jawa Siesta and Jawa Pack. Clone cards: Tatooine locations, sandcrawlers, Jawa weapons, and Utinni! Stakes: One device or droid with out armor.", "lore": "R'kik D'nec remains undefeated in this version of sabacc. Or at least there are no witnesses to the contrary."}, "counterpart": "Dune Sea Sabacc", "combo": ["Dune Sea Sabacc + R'kik D'nec, Hero Of The Dune Sea", "Dune Sea Sabacc + Lift Tube Escape + Lift Tube These two cards can be tracked pretty easily for perfect Sabacc. (Indiana Jones Jedi Knight)"], "legacy": false}]