[{"id": 1505, "gempId": "6_26", "side": "Light", "rarity": "R", "set": "6", "printings": [{"set": "6"}], "front": {"title": "\u2022Leslomy Tacema", "imageUrl": "https://res.starwarsccg.org/cards/JabbasPalace-Light/large/leslomytacema.gif", "type": "Character", "subType": "Alien", "uniqueness": "*", "destiny": "3", "power": "1", "ability": "2", "deploy": "2", "forfeit": "2", "icons": ["Pilot"], "characteristics": ["female"], "gametext": "Adds 3 to power of anything she pilots. While at Audience Chamber, adds 2 to the power bonus provided by Ellorrs Madak.", "lore": "Female Duros. Expert pilot. Helps run the docking facilities in Mos Eisley. Friends with Ellorrs Madak. Approves all cargo manifests. Forgiving of minor transgressions."}, "legacy": false}]