[{"id": 1404, "gempId": "3_12", "side": "Light", "rarity": "R1", "set": "3", "printings": [{"set": "3"}], "front": {"title": "\u2022K-3PO (Kay-Threepio)", "imageUrl": "https://res.starwarsccg.org/cards/Hoth-Light/large/k3pokaythreepio.gif", "type": "Character", "subType": "Droid", "uniqueness": "*", "destiny": "4", "power": "1", "deploy": "2", "forfeit": "3", "gametext": "May initiate battle and be battled. K-3PO is power +1 for each of your other droids at same Hoth or Yavin 4 site. Functions as a leader if present with another of your droids.", "lore": "Old-model protocol droid. Learned military tactics while under the ownership of Commander Narra. In charge of the droid pool at Echo Base. May initiate battle and be battled.", "extraText": ["Protocol Droid"]}, "pulledBy": ["Were You Looking For Me?"], "legacy": false}]