[{"id": 1860, "gempId": "8_23", "side": "Light", "rarity": "R", "set": "8", "printings": [{"set": "8"}], "front": {"title": "\u2022Orrimaarko", "imageUrl": "https://res.starwarsccg.org/cards/Endor-Light/large/orrimaarko.gif", "type": "Character", "subType": "Rebel", "uniqueness": "*", "destiny": "1", "power": "4", "ability": "4", "deploy": "5", "forfeit": "4", "icons": ["Warrior"], "characteristics": ["leader", "scout"], "gametext": "When Orrimaarko is in a battle you just won against an Imperial, opponent must lose 2 Force. Immune to attrition < 3 (or < 4 when present at a forest, jungle or exterior Endor site).", "lore": "Dresselian Scout and resistance leader. Worked tirelessly to combat the subjugation of his homeworld before Bothans brought him into contact with the Alliance.", "extraText": ["Force-Sensitive"]}, "pulledBy": ["Yavin 4: Massassi War Room (V)"], "legacy": false}]