[{"id": 2569, "gempId": "8_62", "side": "Light", "rarity": "R", "set": "8", "printings": [{"set": "8"}], "front": {"title": "\u2022This Is Absolutely Right", "imageUrl": "https://res.starwarsccg.org/cards/Endor-Light/large/thisisabsolutelyright.gif", "type": "Interrupt", "subType": "Used", "uniqueness": "*", "destiny": "5", "gametext": "If Han and Leia are present together at a battleground site (and neither is Undercover), choose one of the following: Your Force drain is +1 at that site this turn. OR Opponent's Force drains at related locations are -1 next turn. OR Cancel This Is Still Wrong.", "lore": "'He's my brother.'"}, "combo": ["A brief list of some cards that work explicitly with Han and Liea: I Know, Count Me In, Wookiee Guide, Someone Who Loves You, This Is Even Better."], "cancels": ["This Is Still Wrong"], "legacy": false}]