[{"id": 64, "gempId": "2_43", "side": "Light", "rarity": "U1", "set": "2", "printings": [{"set": "2"}], "front": {"title": "Advance Preparation", "imageUrl": "https://res.starwarsccg.org/cards/ANewHope-Light/large/advancepreparation.gif", "type": "Interrupt", "subType": "Used Or Lost", "destiny": "6", "gametext": "USED: Place out of play any one of the following from your hand: Attack Run, You're All Clear Kid, Death Star: Trench or Rebel Tech. Retrieve 1 Force.  LOST: Use 3 Force to retrieve Attack Run.", "lore": "Early warning and careful planning allow the Rebels to achieve maximum readiness while still maintaining optimal flexibility."}, "pulledBy": ["Firin Morett"], "legacy": false}]