[{"id": 1790, "gempId": "13_79", "side": "Dark", "rarity": "PM", "set": "13", "printings": [{"set": "13"}], "front": {"title": "\u2022No Match For A Sith", "imageUrl": "https://res.starwarsccg.org/cards/ReflectionsIII-Dark/large/nomatchforasith.gif", "type": "Interrupt", "subType": "Lost", "uniqueness": "*", "destiny": "4", "icons": ["Episode I"], "gametext": "If Maul armed with a lightsaber in battle, use 2 Force to draw two destiny. Opponent draws two destiny. If any of your destinies equal any of opponent's destinies, opponent's Jedi is power = 0 for remainder of battle.", "lore": "Lightsaber duels are so fast and furious that Jedi don't plan their offensive strategy, but instead rely on instinct and their ability to sense an opponent's next strike."}, "legacy": false}]