[{"id": 2521, "gempId": "13_88", "side": "Dark", "rarity": "PM", "set": "13", "printings": [{"set": "13"}], "front": {"title": "\u2022The Ebb Of Battle", "imageUrl": "https://res.starwarsccg.org/cards/ReflectionsIII-Dark/large/theebbofbattle.gif", "type": "Interrupt", "subType": "Used", "uniqueness": "*", "destiny": "5", "icons": ["Episode I"], "gametext": "Activate 1 Force. OR Add 1 to your just-drawn duel destiny. OR If under your Dark Jedi as one of that character's combat cards, reveal to opponent and place in your Lost Pile to cancel an opponent's Force drain.", "lore": "Lightsaber confrontations are a complex dance of feints, strikes, parries and footwork. Mistakes are rarely forgiven."}, "cancels": ["An opponent's Force drain"], "legacy": false}]