[{"id": 2477, "gempId": "106_18", "side": "Dark", "rarity": "PM", "set": "106", "printings": [{"set": "106"}], "front": {"title": "\u2022Tatooine: Tusken Canyon", "imageUrl": "https://res.starwarsccg.org/cards/OfficialTournamentSealedDeck-Dark/large/tatooinetuskencanyon.gif", "type": "Location", "subType": "Site", "uniqueness": "*", "destiny": "0", "icons": ["Exterior", "Planet"], "lightSideIcons": 1, "darkSideIcons": 1, "gametext": "Dark:  If you control, Force drain +1 here (+2 if a Gaderffi Stick is present).  Light:"}, "pulledBy": ["Imperial Entanglements", "Neimoidian Advisor"], "combo": ["Tatooine: Tusken Canyon + Tusken Raiders + Gaderffii Sticks + Darth Vader + Vader's Lightsaber This is a powerful combination. With four Raiders plus Vader, you have 16 power and a destiny draw, as well as a swipe with the Lightsaber. If your opponent threatens to kill Vader or one of the Raiders, simply knock away his weapon as quickly as possible. Add in Snipers to take care of Undercover spies, and you have a fairly stable Force drain."], "legacy": false}]