[{"id": 2270, "gempId": "11_86", "side": "Dark", "rarity": "C", "set": "11", "printings": [{"set": "11"}], "front": {"title": "\u2022Sith Fury", "imageUrl": "https://res.starwarsccg.org/cards/Tatooine-Dark/large/sithfury.gif", "type": "Interrupt", "subType": "Used Or Lost", "uniqueness": "*", "destiny": "4", "gametext": "USED: During a battle, lose one of your lightsabers in that battle to cause all non-unique aliens present to be lost.  LOST: If a duel was just initiated, draw 2 destiny. Opponent draws 3 destiny. If the player with the lower total loses the duel, that player loses 6 Force.", "lore": "At his peak, no one could stand up to the Dark Lord of the Sith. His superior tactics devastated those who opposed him."}, "legacy": false}]