[{"id": 1357, "gempId": "6_165", "side": "Dark", "rarity": "U", "set": "6", "printings": [{"set": "6"}], "front": {"title": "\u2022Jabba's Palace: Entrance Cavern", "imageUrl": "https://res.starwarsccg.org/cards/JabbasPalace-Dark/large/jabbaspalaceentrancecavern.gif", "type": "Location", "subType": "Site", "uniqueness": "*", "destiny": "0", "icons": ["Interior", "Exterior", "Planet"], "lightSideIcons": 0, "darkSideIcons": 1, "gametext": "Dark:  Bib Fortuna deploys -3 here. If you control, with a Gamorrean here, Force drain +1 here.  Light:  If you control, Force drain +1 here and your aliens deploy -2 here."}, "pulledBy": ["Tatooine: Jabba's Palace"], "counterpart": "Jabba's Palace: Entrance Cavern", "canceledBy": ["B'omarr Monk cancels Jabba's Palace Dark Side game text where present"], "legacy": false}]