[{"id": 916, "gempId": "3_124", "side": "Dark", "rarity": "U1", "set": "3", "printings": [{"set": "3"}], "front": {"title": "Exposure", "imageUrl": "https://res.starwarsccg.org/cards/Hoth-Dark/large/exposure.gif", "type": "Interrupt", "subType": "Lost", "destiny": "2", "gametext": "Use X Force during your control phase, where X = the total number of characters present or missing at exterior marker sites under 'nighttime conditions.' Those characters are lost.", "lore": "'Artoo says the chances of survival are 125 to 1.'"}, "legacy": false}]