[{"id": 1832, "gempId": "10_44", "side": "Dark", "rarity": "PM", "set": "10", "printings": [{"set": "10"}], "front": {"title": "Ommni Box & It's Worse", "imageUrl": "https://res.starwarsccg.org/cards/ReflectionsII-Dark/large/ommnibox&itsworse.gif", "type": "Interrupt", "subType": "Used Or Lost", "destiny": "5", "gametext": "USED: Shuffle any player's Reserve Deck or Lost Pile.  LOST: If It Could Be Worse was just played, it is canceled and you may use X Force to raise damage against opponent by X amount. OR If opponent just lost Force from a battle, play to increase loss by 1 Force."}, "counterpart": "The Bith Shuffle & Desperate Reach", "canceledBy": ["It's A Hit!"], "cancels": ["It Could Be Worse"], "legacy": false}]