[{"id": 6021, "gempId": "211_50", "side": "Light", "rarity": "C", "set": "211", "printings": [{"set": "211"}], "front": {"title": "\u2022Where's Han?", "imageUrl": "https://res.starwarsccg.org/cards/Virtual11-Light/large/whereshan.gif", "type": "Interrupt", "subType": "Used Or Lost", "destiny": "4", "icons": ["Episode VII"], "gametext": "USED: Take Han's Dice or non-[Maintenance] Han into hand from Reserve Deck; reshuffle.  LOST: If you just lost a gambler, take that gambler into hand. OR Once per game, exchange a card in hand with a Resistance Agent or [Episode VII] Skywalker in Lost Pile.", "lore": "Blank."}, "legacy": false}]