[{"id": 1385, "gempId": "200_54", "side": "Light", "rarity": "R", "set": "200", "printings": [{"set": "200"}], "front": {"title": "Jedi Levitation (V)", "imageUrl": "https://res.starwarsccg.org/cards/Virtual0-Light/large/jedilevitation.gif", "type": "Interrupt", "subType": "Used Or Lost", "destiny": "4", "icons": ["Dagobah"], "gametext": "USED: If you just drew a character for destiny, take that card into hand to cancel and redraw that destiny.  LOST: Use 3 Force to retrieve a non-[Maintenance] character into hand.", "lore": "A Jedi can adjust the Force within and around an object, causing it to move as the Jedi wills."}, "pulledBy": ["Yoda's Hope"], "counterpart": "Sith Fury (V)", "legacy": false}]