[{"id": 6901, "gempId": "215_27", "side": "Dark", "rarity": "C2", "set": "215", "printings": [{"set": "215"}], "front": {"title": "\u2022Ubrikkian Industries", "imageUrl": "https://res.starwarsccg.org/cards/Virtual15-Dark/large/ubrikkianindustries.gif", "type": "Effect", "uniqueness": "*", "destiny": "4", "gametext": "Deploy on table. During your deploy phase, may reveal an alien with 'vehicle' in game text from hand to take a transport vehicle into hand (or vice versa) and deploy both simultaneously. Your drivers are immune to Clash Of Sabers. Immune to Alter.", "lore": "Blank."}, "pulledBy": ["Twi'lek Advisor", "We Must Accelerate Our Plans"], "rulings": ["The 'vice versa' function still requires the alien (not the transport vehicle) to have the word 'vehicle' in game text.", "The alien must deploy aboard the transport vehicle.", "If the deployment is not possible, return the card taken from Reserve Deck back to that deck and reshuffle."], "legacy": false}]