[{"id": 1785, "gempId": "4_28", "side": "Light", "rarity": "R", "set": "4", "printings": [{"set": "4"}], "front": {"title": "\u2022No Disintegrations!", "imageUrl": "https://res.starwarsccg.org/cards/Dagobah-Light/large/nodisintegrations.gif", "type": "Effect", "uniqueness": "*", "destiny": "4", "gametext": "Use 2 Force to deploy on your side of table. If a Rebel of ability > 2 is lost (not captured) during a battle involving an opponent's bounty hunter, opponent loses 3 Force. If Vader on table, one bounty hunter involved in that battle (your choice) is also lost.", "lore": "'There will be a substantial reward for the one who finds the Millennium Falcon. You are free to use any methods necessary, but I want them alive.'"}, "pulledBy": ["The Signal", "We Wish To Board At Once"], "canceledBy": ["Point Man"], "legacy": false}]