[{"id": 5123, "gempId": "205_22", "side": "Dark", "rarity": "R", "set": "205", "printings": [{"set": "205"}], "front": {"title": "\u2022Boba Fett's Blaster Rifle (V)", "imageUrl": "https://res.starwarsccg.org/cards/Virtual5-Dark/large/bobafettsblasterrifle.gif", "type": "Weapon", "subType": "Character", "uniqueness": "*", "destiny": "1", "characteristics": ["blaster rifle", "rifle"], "gametext": "Deploy on your non-[maintenance] bounty hunter. If on Boba Fett, once per game, during your move phase, may use 2 Force to relocate him (with any captive he is escorting) to a [Jabba's Palace] site. May target a character or vehicle for free. Draw destiny. Target hit if destiny +2 > defense value.", "lore": "Sawed off BlasTech EE-3 blaster rifle. Although its barrel is a few centimeters under the legal limit, no one has lived to file an official complaint."}, "pulledBy": ["Any Methods Necessary (V)", "Jabba's Through With You"], "matchingWeapon": ["Boba Fett", "Boba Fett (CC)", "Boba Fett (CC) (V)"], "canceledBy": ["Game text canceled by Mandalorian Mishap"], "legacy": false}]