[{"id": 506, "gempId": "7_12", "side": "Light", "rarity": "R", "set": "7", "printings": [{"set": "105"}, {"set": "7"}], "front": {"title": "\u2022Commander Wedge Antilles", "imageUrl": "https://res.starwarsccg.org/cards/SpecialEdition-Light/large/commanderwedgeantilles.gif", "type": "Character", "subType": "Rebel", "uniqueness": "*", "destiny": "3", "power": "3", "ability": "2", "deploy": "3", "forfeit": "6", "icons": ["Pilot", "Warrior"], "characteristics": ["commander", "leader", "Corellian", "Rogue Squadron pilot"], "gametext": "Adds 3 to power of anything he pilots. When piloting Rogue 3, also adds 2 to maneuver and draws battle destiny if not able to otherwise. May use 2 Force to take one One More Pass into hand from Reserve Deck; reshuffle.", "lore": "Promoted to commander for his heroism in the Battle of Yavin. Leader in charge of training new pilots assigned to Echo Base. Piloted Rogue 3 in the battle of Hoth."}, "pulls": ["One More Pass"], "pulledBy": ["Beldon's Eye (V)", "Echo Base Garrison", "Princess Organa", "Yavin 4: Massassi War Room (V)"], "matching": ["Pulsar Skate", "Red 2", "Red Squadron 1", "Rogue 3"], "legacy": false}]