[{"id": 1540, "gempId": "7_30", "side": "Light", "rarity": "R", "set": "7", "printings": [{"set": "7"}], "front": {"title": "\u2022Lieutenant Tarn Mison", "imageUrl": "https://res.starwarsccg.org/cards/SpecialEdition-Light/large/lieutenanttarnmison.gif", "type": "Character", "subType": "Rebel", "uniqueness": "*", "destiny": "3", "power": "1", "ability": "2", "deploy": "2", "forfeit": "4", "icons": ["Pilot"], "gametext": "Deploys -1 aboard your unique (\u2022) Rebel starfighter. Adds 2 to power of anything he pilots. When starfighter he pilots fires a starship weapon, characters aboard target are forfeit = 0 for remainder of turn.", "lore": "Former Imperial pilot. Joined the Alliance shortly after the Battle of Yavin. Flew cover for Bright Hope during the evacuation of Hoth. Expert marksman."}, "legacy": false}]